cloudicorn/__init__.py
cloudicorn/cloudicorn.py
cloudicorn/core/__init__.py
cloudicorn/core/core.py
cloudicorn/setup/__init__.py
cloudicorn/setup/setup.py
cloudicorn/tfwrapper/__init__.py
cloudicorn/tfwrapper/tfwrapper.py
cloudicorn_cli-0.10.dist-info/METADATA
cloudicorn_cli-0.10.dist-info/WHEEL
cloudicorn_cli-0.10.dist-info/entry_points.txt
cloudicorn_cli-0.10.dist-info/top_level.txt
cloudicorn_cli-0.10.dist-info/RECORD
