Metadata-Version: 2.1
Name: cloudicorn-cli
Version: 0.10
Summary: Taking Infrastructure As Code to the next level
Home-page: https://github.com/jumidev/cloudicorn-cli
Author: krezreb
Author-email: josephbeeson@gmail.com
License: MIT
Keywords: build_date:2024-11-28
Requires-Dist: PyCryptodome
Requires-Dist: fuzzywuzzy
Requires-Dist: gitpython
Requires-Dist: prompt-toolkit
Requires-Dist: pyfiglet
Requires-Dist: pyhcl
Requires-Dist: python-Levenshtein
Requires-Dist: python-dotenv
Requires-Dist: pyyaml
Requires-Dist: requests
Requires-Dist: urllib3 <2
